{
    "game": {
        "id": "b18ddc1abc72c8c98573d1faa4da6894355e747c",
        "table": {
            "id": "d6c41934d70c9d3f3edd67889ea8e236275bd9b2",
            "name": "Tennessee 🥃"
        },
        "winner": {
            "id": "discord-708836607196790826",
            "username": "CraigCraig"
        },
        "losers": [
            {
                "id": "313c21bd9162d969e5745bd1c9feb8d090040687",
                "username": "Shap Diesel",
                "bot": false
            },
            {
                "id": "discord-458751755447042059",
                "username": "jpuck",
                "bot": false
            },
            {
                "id": "discord-525136093998350346",
                "username": "RoboMoti",
                "bot": false
            }
        ]
    },
    "submitted_at": "2021-10-24T06:19:29.804Z",
    "submitted_by": {
        "id": "discord-458751755447042059",
        "username": "jpuck",
        "avatar_url": "https://cdn.discordapp.com/avatars/458751755447042059/7eabed1f1aedde90b49d78b286b1a4b0"
    }
}